cli/__init__.py
cli/config.py
cli/main.py
cli/client/__init__.py
cli/client/comments.py
cli/client/error_handler.py
cli/client/exceptions.py
cli/client/projects.py
cli/client/pull_requests.py
cli/client/tasks.py
cli/client/users.py
cli/client/workspaces.py
cli/commands/__init__.py
cli/commands/agent.py
cli/commands/comment.py
cli/commands/config_commands.py
cli/commands/console.py
cli/commands/context.py
cli/commands/decorators.py
cli/commands/formatters.py
cli/commands/guards.py
cli/commands/health.py
cli/commands/init.py
cli/commands/login.py
cli/commands/self_update.py
cli/commands/services.py
cli/commands/utils.py
cli/commands/validators.py
cli/commands/board/__init__.py
cli/commands/board/commands.py
cli/commands/board/formatters.py
cli/commands/board/renderers.py
cli/commands/helpers/__init__.py
cli/commands/helpers/formatting.py
cli/commands/helpers/identifiers.py
cli/commands/helpers/planning.py
cli/commands/helpers/workspace.py
cli/commands/sync/__init__.py
cli/commands/sync/converters.py
cli/commands/sync/open.py
cli/commands/sync/pull.py
cli/commands/sync/push.py
cli/commands/task/__init__.py
cli/commands/task/dependencies.py
cli/commands/task/helpers.py
cli/commands/task/list.py
cli/commands/task/pick.py
cli/commands/task/plan.py
cli/commands/task/pr.py
cli/commands/task/start.py
cli/commands/task/suggest.py
cli/commands/task/unpick.py
cli/commands/task/crud/__init__.py
cli/commands/task/crud/create.py
cli/commands/task/crud/delete.py
cli/commands/task/crud/edit_helpers.py
cli/commands/task/crud/read.py
cli/commands/task/crud/update.py
cli/data/agent_commands/claude/anyt-done.md
cli/data/agent_commands/claude/anyt-pr.md
cli/data/agent_commands/claude/anyt-status.md
cli/data/agent_commands/codex/anyt-done.md
cli/data/agent_commands/codex/anyt-new.md
cli/data/agent_commands/codex/anyt-next.md
cli/data/agent_commands/codex/anyt-pr.md
cli/data/agent_commands/codex/anyt-status.md
cli/data/agent_commands/codex/anyt-work.md
anyt-0.11.3.dist-info/METADATA
anyt-0.11.3.dist-info/WHEEL
anyt-0.11.3.dist-info/entry_points.txt
anyt-0.11.3.dist-info/licenses/LICENSE
anyt-0.11.3.dist-info/RECORD
