Metadata-Version: 2.4
Name: anyt
Version: 0.11.3
Summary: AI-native task management CLI for coding agents and human developers
Project-URL: Homepage, https://anyt.dev
Project-URL: Documentation, https://anyt.dev/docs/cli
Project-URL: Support, https://anyt.dev/support
Author-email: AnyTransformer Inc <contact@anytransformer.com>
Maintainer-email: AnyTransformer Inc <contact@anytransformer.com>
License: Proprietary
License-File: LICENSE
Keywords: ai,cli,developer-tools,productivity,task-management
Classifier: Development Status :: 3 - Alpha
Classifier: Intended Audience :: Developers
Classifier: License :: Other/Proprietary License
Classifier: Programming Language :: Python :: 3
Classifier: Programming Language :: Python :: 3.12
Classifier: Topic :: Software Development :: Libraries :: Python Modules
Classifier: Topic :: Utilities
Requires-Python: <3.14,>=3.12
Requires-Dist: httpx>=0.28.1
Requires-Dist: inquirerpy>=0.3.4
Requires-Dist: jinja2>=3.1.0
Requires-Dist: keyring>=25.0.0
Requires-Dist: mcp>=1.17.0
Requires-Dist: nest-asyncio>=1.6.0
Requires-Dist: packaging>=24.0
Requires-Dist: pydantic>=2.11.9
Requires-Dist: pyperclip>=1.8.2
Requires-Dist: python-dotenv>=1.0.0
Requires-Dist: pyyaml>=6.0
Requires-Dist: rich>=14.0.0
Requires-Dist: tenacity>=9.1.2
Requires-Dist: typer>=0.15.3
